{
  "project_info": {
    "project_number": "287791020361",
    "project_id": "helical-realm-365608",
    "storage_bucket": "helical-realm-365608.appspot.com"
  },
  "client": [
    {
      "client_info": {
        "mobilesdk_app_id": "1:287791020361:android:e998e10b46f5e786e4c298",
        "android_client_info": {
          "package_name": "com.example.bhopu"
        }
      },
      "oauth_client": [
        {
          "client_id": "287791020361-7eb1boboj2vri2lndcuklksa8gqg35rr.apps.googleusercontent.com",
          "client_type": 3
        }
      ],
      "api_key": [
        {
          "current_key": "AIzaSyCBi2vcBfoHTRfjBeJr4nZlSZvsD4tAmJg"
        }
      ],
      "services": {
        "appinvite_service": {
          "other_platform_oauth_client": [
            {
              "client_id": "287791020361-7eb1boboj2vri2lndcuklksa8gqg35rr.apps.googleusercontent.com",
              "client_type": 3
            }
          ]
        }
      }
    }
  ],
  "configuration_version": "1"
}